httpx_caching/__init__.py
httpx_caching/_heuristics.py
httpx_caching/_models.py
httpx_caching/_policy.py
httpx_caching/_serializer.py
httpx_caching/_types.py
httpx_caching/_utils.py
httpx_caching/_wrapper.py
httpx_caching/_async/__init__.py
httpx_caching/_async/_cache.py
httpx_caching/_async/_transport.py
httpx_caching/_sync/__init__.py
httpx_caching/_sync/_cache.py
httpx_caching/_sync/_transport.py
tests/__init__.py
tests/conftest.py
tests/test_max_age.py
tests/test_serialization.py
tests/test_server_http_version.py
tests/_async/__init__.py
tests/_async/test_chunked_response.py
tests/_async/test_client_actions.py
tests/_async/test_etag.py
tests/_async/test_expires_heuristics.py
tests/_async/test_redirects.py
tests/_async/test_vary.py
http_caching4-0.1.0.dist-info/METADATA
http_caching4-0.1.0.dist-info/WHEEL
http_caching4-0.1.0.dist-info/top_level.txt
http_caching4-0.1.0.dist-info/RECORD
