Metadata-Version: 2.1
Name: http-caching4
Version: 0.1.0
Summary: Caching support for Async httpx Client. Cloned from https://github.com/kovan/httpx-caching, https://github.com/johtso/httpx-caching
Home-page: https://github.com/ms280690/httpx-caching4.git
Author: Mehul Solanki
Author-email: ms280690@gmail.com
License: UNKNOWN
Platform: UNKNOWN
Requires-Python: >=3.8
Requires-Dist: httpx (==0.18.*)
Requires-Dist: msgpack
Requires-Dist: anyio
Requires-Dist: multimethod
Provides-Extra: dev
Requires-Dist: pytest ; extra == 'dev'
Requires-Dist: pytest-cov ; extra == 'dev'
Requires-Dist: pytest-asyncio ; extra == 'dev'
Requires-Dist: pytest-mock ; extra == 'dev'
Requires-Dist: pytest-timeout ; extra == 'dev'
Requires-Dist: mock ; extra == 'dev'
Requires-Dist: types-mock ; extra == 'dev'
Requires-Dist: cherrypy ; extra == 'dev'
Requires-Dist: freezegun ; extra == 'dev'
Requires-Dist: types-freezegun ; extra == 'dev'
Requires-Dist: autoflake ; extra == 'dev'
Requires-Dist: black ; extra == 'dev'
Requires-Dist: isort ; extra == 'dev'
Requires-Dist: flake8 ; extra == 'dev'
Requires-Dist: flake8-bugbear ; extra == 'dev'
Requires-Dist: mypy ; extra == 'dev'
Requires-Dist: unasync ; extra == 'dev'
Requires-Dist: types-dataclasses ; extra == 'dev'
